LICENSE
README.md
zdppy_yaml/__init__.py
zdppy_yaml/libs/__init__.py
zdppy_yaml/libs/yaml/__init__.py
zdppy_yaml/libs/yaml/composer.py
zdppy_yaml/libs/yaml/constructor.py
zdppy_yaml/libs/yaml/cyaml.py
zdppy_yaml/libs/yaml/dumper.py
zdppy_yaml/libs/yaml/emitter.py
zdppy_yaml/libs/yaml/error.py
zdppy_yaml/libs/yaml/events.py
zdppy_yaml/libs/yaml/loader.py
zdppy_yaml/libs/yaml/nodes.py
zdppy_yaml/libs/yaml/parser.py
zdppy_yaml/libs/yaml/reader.py
zdppy_yaml/libs/yaml/representer.py
zdppy_yaml/libs/yaml/resolver.py
zdppy_yaml/libs/yaml/scanner.py
zdppy_yaml/libs/yaml/serializer.py
zdppy_yaml/libs/yaml/tokens.py
zdppy_yaml/zdppy_yaml.py
zdppy_yaml-0.1.1.dist-info/LICENSE
zdppy_yaml-0.1.1.dist-info/WHEEL
zdppy_yaml-0.1.1.dist-info/METADATA
zdppy_yaml-0.1.1.dist-info/RECORD
